setup.py
OSR/__init__.py
OSR/getinfo.py
OSR/radio.py
OSR/songs.py
OSR.egg-info/PKG-INFO
OSR.egg-info/SOURCES.txt
OSR.egg-info/dependency_links.txt
OSR.egg-info/requires.txt
OSR.egg-info/top_level.txt