Metadata-Version: 1.0
Name: OSR
Version: 0.0.1
Summary: Automated DJ/Announcer
Home-page: UNKNOWN
Author: Julian K. Arni
Author-email: jkarni@gmail.com
License: EPL
Platform: UNKNOWN
